finecode_extension_runner/__init__.py
finecode_extension_runner/__main__.py
finecode_extension_runner/_version.py
finecode_extension_runner/action_utils.py
finecode_extension_runner/app_dirs.py
finecode_extension_runner/cli.py
finecode_extension_runner/context.py
finecode_extension_runner/domain.py
finecode_extension_runner/global_state.py
finecode_extension_runner/logs.py
finecode_extension_runner/lsp_server.py
finecode_extension_runner/partial_result_sender.py
finecode_extension_runner/project_dirs.py
finecode_extension_runner/py.typed
finecode_extension_runner/run_utils.py
finecode_extension_runner/schemas.py
finecode_extension_runner/services.py
finecode_extension_runner/start.py
finecode_extension_runner/_services/__init__.py
finecode_extension_runner/_services/run_action.py
finecode_extension_runner/action_handlers/__init__.py
finecode_extension_runner/action_handlers/dependency_config_utils.py
finecode_extension_runner/action_handlers/dump_config.py
finecode_extension_runner/action_handlers/dump_config_save.py
finecode_extension_runner/action_handlers/prepare_envs_install_deps.py
finecode_extension_runner/action_handlers/prepare_envs_read_configs.py
finecode_extension_runner/action_handlers/prepare_runners_install_runner_and_presets.py
finecode_extension_runner/action_handlers/prepare_runners_read_configs.py
finecode_extension_runner/di/__init__.py
finecode_extension_runner/di/_state.py
finecode_extension_runner/di/bootstrap.py
finecode_extension_runner/di/resolver.py
finecode_extension_runner/impls/__init__.py
finecode_extension_runner/impls/action_runner.py
finecode_extension_runner/impls/command_runner.py
finecode_extension_runner/impls/file_manager.py
finecode_extension_runner/impls/inmemory_cache.py
finecode_extension_runner/impls/loguru_logger.py
finecode_extension_runner/impls/process_executor.py
finecode_extension_runner/impls/project_info_provider.py
finecode_extension_runner/utils/__init__.py
finecode_extension_runner-0.3.dist-info/METADATA
finecode_extension_runner-0.3.dist-info/WHEEL
finecode_extension_runner-0.3.dist-info/top_level.txt
finecode_extension_runner-0.3.dist-info/RECORD
