Metadata-Version: 2.4
Name: finecode_extension_runner
Version: 0.3
Summary: Extension runner component for FineCode
Author-email: Vladyslav Hnatiuk <aders1234@gmail.com>
Requires-Python: <3.14,>=3.11
Requires-Dist: loguru==0.7.*
Requires-Dist: tomlkit==0.11.*
Requires-Dist: click==8.1.*
Requires-Dist: pydantic==2.10.*
Requires-Dist: platformdirs==4.3.*
Requires-Dist: pygls==2.0.0-a2
Requires-Dist: finecode_extension_api==0.3.*
Requires-Dist: deepmerge==2.0.*
